dearmep/__init__.py
dearmep/config.py
dearmep/example-config.yaml
dearmep/http_client.py
dearmep/l10n.py
dearmep/logging.yaml
dearmep/main.py
dearmep/markdown_files.py
dearmep/models.py
dearmep/progress.py
dearmep/ratelimit.py
dearmep/api/__init__.py
dearmep/api/authtoken.py
dearmep/api/v1.py
dearmep/cli/__init__.py
dearmep/cli/__main__.py
dearmep/cli/check.py
dearmep/cli/convert.py
dearmep/cli/db.py
dearmep/cli/dump.py
dearmep/cli/importing.py
dearmep/cli/run_alembic.py
dearmep/cli/serve.py
dearmep/cli/version.py
dearmep/convert/__init__.py
dearmep/convert/audio.py
dearmep/convert/blobfile.py
dearmep/convert/dump.py
dearmep/convert/ffmpeg.py
dearmep/convert/image.py
dearmep/convert/lz.py
dearmep/convert/tabular.py
dearmep/convert/xml.py
dearmep/convert/europarl/__init__.py
dearmep/convert/europarl/media.py
dearmep/convert/europarl/rollcallvote.py
dearmep/convert/parltrack/__init__.py
dearmep/convert/parltrack/mep.py
dearmep/database/__init__.py
dearmep/database/connection.py
dearmep/database/importing.py
dearmep/database/lint.py
dearmep/database/models.py
dearmep/database/query.py
dearmep/migrations/alembic.ini
dearmep/migrations/env.py
dearmep/migrations/script.py.mako
dearmep/migrations/script.py.mako.license
dearmep/migrations/versions/20231121-8d7e440490bf_inital_alembic_database_state.py
dearmep/migrations/versions/20231214-5d2aefe5f0ad_add_scheduler_relevant_tables.py
dearmep/phone/__init__.py
dearmep/phone/abstract.py
dearmep/phone/developer_phone.py
dearmep/phone/elks_phone.py
dearmep/phone/ivr.py
dearmep/phone/elks/__init__.py
dearmep/phone/elks/elks.py
dearmep/phone/elks/metrics.py
dearmep/phone/elks/models.py
dearmep/phone/elks/ongoing_calls.py
dearmep/phone/elks/utils.py
dearmep/schedules/__init__.py
dearmep/schedules/calls.py
dearmep/static_files/__init__.py
dearmep/static_files/demo.html
dearmep/static_files/static/dear-mep-inner.css
dearmep/static_files/static/dear-mep.css
dearmep/static_files/static/dear-mep.js
dearmep/static_files/static/flags.css
dearmep-4.0.0.dist-info/METADATA
dearmep-4.0.0.dist-info/WHEEL
dearmep-4.0.0.dist-info/entry_points.txt
dearmep-4.0.0.dist-info/RECORD
