Metadata-Version: 2.4
Name: DearMEP
Version: 4.0.0
Summary: DearMEP helps people contact their representatives.
Project-URL: homepage, https://dearmep.eu/
Project-URL: source, https://github.com/AKVorrat/dearmep
Project-URL: documentation, https://github.com/AKVorrat/dearmep/blob/main/README.md
Project-URL: issues, https://github.com/AKVorrat/dearmep/issues
Author: Tim Weber, Tobias Mühlberger, iameru, Philipp Aaron Becker, Jörn Bethune
Maintainer: Tim Weber
Classifier: Development Status :: 5 - Production/Stable
Classifier: Environment :: Console
Classifier: Environment :: Web Environment
Classifier: Framework :: FastAPI
Classifier: License :: OSI Approved :: GNU Affero General Public License v3 or later (AGPLv3+)
Classifier: Operating System :: POSIX
Classifier: Programming Language :: Python :: 3 :: Only
Classifier: Programming Language :: Python :: 3.9
Classifier: Programming Language :: Python :: 3.10
Classifier: Programming Language :: Python :: 3.11
Classifier: Programming Language :: Python :: 3.12
Classifier: Programming Language :: Python :: 3.13
Classifier: Topic :: Communications :: Telephony
Requires-Python: <4,>=3.9
Requires-Dist: alembic~=1.12.1
Requires-Dist: backoff~=2.2.1
Requires-Dist: canonicaljson~=2.0.0
Requires-Dist: countryguess~=0.3.0
Requires-Dist: defusedxml~=0.7.1
Requires-Dist: fastapi-restful~=0.5.0
Requires-Dist: fastapi~=0.115.6
Requires-Dist: httpx~=0.23.3
Requires-Dist: jinja2~=3.1.4
Requires-Dist: limits~=3.14
Requires-Dist: lzip~=1.2.0
Requires-Dist: markdown-it-py~=2.2.0
Requires-Dist: phonenumbers~=8.13.22
Requires-Dist: pillow~=11.0
Requires-Dist: pydantic<2,>=1.10.16
Requires-Dist: pyjwt>=2.10.1
Requires-Dist: python-dotenv~=1.0.0
Requires-Dist: python-geoacumen>=2023
Requires-Dist: python-multipart~=0.0.20
Requires-Dist: pytz~=2023.3.post1
Requires-Dist: pyyaml~=6.0
Requires-Dist: ratelimit~=2.2.1
Requires-Dist: rich~=13.9
Requires-Dist: sqlmodel<0.0.11
Requires-Dist: starlette-exporter~=0.15.1
Requires-Dist: uvicorn[standard]~=0.32
Provides-Extra: convert
Requires-Dist: csvkit>=2; extra == 'convert'
Requires-Dist: visidata>=3; extra == 'convert'
Requires-Dist: xlsxwriter~=3.1; extra == 'convert'
Provides-Extra: specs
Requires-Dist: eralchemy2~=1.4; extra == 'specs'
